soundfactory/image_base.py
soundfactory/signal_base.py
soundfactory/cli.py
soundfactory/play.py
soundfactory/view.py
soundfactory/constants.py
soundfactory/signal_builder.py
soundfactory/__init__.py
soundfactory/signal_plotter.py
soundfactory/create.py
soundfactory/cyutils/builder_utils.c
soundfactory/cyutils/builder_utils.cpython-38-x86_64-linux-gnu.so
soundfactory/utils/scale.py
soundfactory/utils/builder_utils.py
soundfactory/utils/__init__.py
soundfactory/utils/labels.py
soundfactory/utils/signal.py
soundfactory/utils/helpers.py
soundfactory/utils/plot.py
soundfactory/settings/input_validators.py
soundfactory/settings/builder_cache.pickle
soundfactory/settings/__init__.py
soundfactory/settings/logging_settings.py
soundfactory/settings/config.py
soundfactory/settings/signal.py
soundfactory/settings/plot.py
soundfactory/settings/fonts/FreeSerif.otf
soundfactory-0.2.1.dist-info/entry_points.txt
soundfactory-0.2.1.dist-info/WHEEL
soundfactory-0.2.1.dist-info/LICENSE
soundfactory-0.2.1.dist-info/top_level.txt
soundfactory-0.2.1.dist-info/RECORD
soundfactory-0.2.1.dist-info/METADATA
