Metadata-Version: 2.1
Name: soundfactory
Version: 0.2.1
Summary: simple tools for audio-signal manipulations
Home-page: https://gitlab.com/babaMar/soundfactory
Author: TSAK
Author-email: tsakians@gmail.com
License: MIT
Platform: UNKNOWN
Classifier: Environment :: Console
Classifier: Intended Audience :: Science/Research
Classifier: License :: OSI Approved :: MIT License
Classifier: Operating System :: Unix
Classifier: Programming Language :: Python :: 3
Classifier: Topic :: Artistic Software
Classifier: Topic :: Software Development :: Libraries :: Python Modules
Requires-Python: >=3.6
License-File: LICENSE
Requires-Dist: cachetools (==4.2.2)
Requires-Dist: cffi (==1.14.5)
Requires-Dist: Click (==8.0.1)
Requires-Dist: complexaudio (==1.0.4)
Requires-Dist: cycler (==0.10.0)
Requires-Dist: cysignals (==1.10.3)
Requires-Dist: Cython (==0.29.23)
Requires-Dist: getch (==1.0)
Requires-Dist: llvmlite (==0.36.0)
Requires-Dist: lxml (==4.6.2)
Requires-Dist: matplotlib (==3.3.4)
Requires-Dist: numba (==0.53.1)
Requires-Dist: numpy (==1.20.3)
Requires-Dist: Pillow (==8.2.0)
Requires-Dist: PyAudio (==0.2.11)
Requires-Dist: pycparser (==2.20)
Requires-Dist: pyparsing (==2.4.7)
Requires-Dist: PySoundFile (==0.9.0.post1)
Requires-Dist: python-dateutil (==2.8.1)
Requires-Dist: python-toolbox (==1.0.11)
Requires-Dist: pytz (==2020.5)
Requires-Dist: scipy (==1.5.4)
Requires-Dist: six (==1.15.0)
Provides-Extra: tests
Requires-Dist: pytest ; extra == 'tests'
Requires-Dist: pytest-mock ; extra == 'tests'
Requires-Dist: pytest-cov ; extra == 'tests'
